{
    "openapi": "3.0.0",
    "info": {
        "title": "E-Commerce API",
        "description": "API Documentation for E-Commerce Platform",
        "contact": {
            "email": "admin@example.com"
        },
        "version": "1.0.0"
    },
    "servers": [
        {
            "url": "http://localhost:8000",
            "description": "Local Development Server"
        }
    ],
    "paths": {
        "/api/register": {
            "post": {
                "tags": [
                    "Authentication"
                ],
                "summary": "Register a new user",
                "description": "Register a new user",
                "operationId": "8a56853624e025573120a09a4c75d468",
                "requestBody": {
                    "required": true,
                    "content": {
                        "application/json": {
                            "schema": {
                                "required": [
                                    "name",
                                    "email",
                                    "password",
                                    "password_confirmation"
                                ],
                                "properties": {
                                    "name": {
                                        "type": "string",
                                        "example": "John Doe"
                                    },
                                    "email": {
                                        "type": "string",
                                        "format": "email",
                                        "example": "john@example.com"
                                    },
                                    "password": {
                                        "type": "string",
                                        "format": "password",
                                        "example": "password123"
                                    },
                                    "password_confirmation": {
                                        "type": "string",
                                        "format": "password",
                                        "example": "password123"
                                    }
                                },
                                "type": "object"
                            }
                        }
                    }
                },
                "responses": {
                    "201": {
                        "description": "Registration successful",
                        "content": {
                            "application/json": {
                                "schema": {
                                    "properties": {
                                        "message": {
                                            "type": "string",
                                            "example": "Registration successful"
                                        },
                                        "user": {
                                            "type": "object"
                                        },
                                        "token": {
                                            "type": "string"
                                        }
                                    },
                                    "type": "object"
                                }
                            }
                        }
                    },
                    "422": {
                        "description": "Validation error"
                    }
                }
            }
        },
        "/api/login": {
            "post": {
                "tags": [
                    "Authentication"
                ],
                "summary": "Login user",
                "description": "Login user",
                "operationId": "a3b306d14572d1f4bd6c064b3233e7b8",
                "requestBody": {
                    "required": true,
                    "content": {
                        "application/json": {
                            "schema": {
                                "required": [
                                    "email",
                                    "password"
                                ],
                                "properties": {
                                    "email": {
                                        "type": "string",
                                        "format": "email",
                                        "example": "john@example.com"
                                    },
                                    "password": {
                                        "type": "string",
                                        "format": "password",
                                        "example": "password123"
                                    }
                                },
                                "type": "object"
                            }
                        }
                    }
                },
                "responses": {
                    "200": {
                        "description": "Login successful",
                        "content": {
                            "application/json": {
                                "schema": {
                                    "properties": {
                                        "token": {
                                            "type": "string"
                                        }
                                    },
                                    "type": "object"
                                }
                            }
                        }
                    },
                    "401": {
                        "description": "Invalid credentials"
                    },
                    "422": {
                        "description": "Validation error"
                    }
                }
            }
        },
        "/api/logout": {
            "post": {
                "tags": [
                    "Authentication"
                ],
                "summary": "Logout user",
                "description": "Logout user",
                "operationId": "fe8f3429cd6979b3b4517e186505f9f9",
                "responses": {
                    "200": {
                        "description": "Logout successful",
                        "content": {
                            "application/json": {
                                "schema": {
                                    "properties": {
                                        "message": {
                                            "type": "string",
                                            "example": "Logout successful"
                                        }
                                    },
                                    "type": "object"
                                }
                            }
                        }
                    },
                    "401": {
                        "description": "Unauthenticated"
                    }
                },
                "security": [
                    {
                        "bearerAuth": []
                    }
                ]
            }
        },
        "/api/user": {
            "get": {
                "tags": [
                    "Authentication"
                ],
                "summary": "Get authenticated user",
                "description": "Get authenticated user",
                "operationId": "7c1cf647d76fad4b3eb1549fa4fe2f4c",
                "responses": {
                    "200": {
                        "description": "User data",
                        "content": {
                            "application/json": {
                                "schema": {
                                    "properties": {
                                        "id": {
                                            "type": "integer"
                                        },
                                        "name": {
                                            "type": "string"
                                        },
                                        "email": {
                                            "type": "string"
                                        }
                                    },
                                    "type": "object"
                                }
                            }
                        }
                    },
                    "401": {
                        "description": "Unauthenticated"
                    }
                },
                "security": [
                    {
                        "bearerAuth": []
                    }
                ]
            }
        },
        "/api/permissions": {
            "get": {
                "tags": [
                    "Permissions"
                ],
                "summary": "Get all permissions",
                "description": "Display a listing of the resource.",
                "operationId": "27bb1606a7b293d1d49f57bb94ae71f7",
                "responses": {
                    "200": {
                        "description": "List of permissions",
                        "content": {
                            "application/json": {
                                "schema": {
                                    "properties": {
                                        "success": {
                                            "type": "boolean",
                                            "example": true
                                        },
                                        "data": {
                                            "type": "array",
                                            "items": {
                                                "properties": {
                                                    "id": {
                                                        "type": "integer",
                                                        "example": 1
                                                    },
                                                    "name": {
                                                        "type": "string",
                                                        "example": "Read Users"
                                                    },
                                                    "type": {
                                                        "type": "string",
                                                        "example": "read"
                                                    },
                                                    "group": {
                                                        "type": "string",
                                                        "example": "users"
                                                    }
                                                },
                                                "type": "object"
                                            }
                                        }
                                    },
                                    "type": "object"
                                }
                            }
                        }
                    },
                    "401": {
                        "description": "Unauthenticated"
                    },
                    "403": {
                        "description": "User is authenticated, but dont have permission **Read Permissions** to access this resource"
                    },
                    "422": {
                        "description": "Validation error"
                    },
                    "500": {
                        "description": "Internal server error"
                    }
                },
                "security": [
                    {
                        "bearerAuth": []
                    }
                ]
            }
        },
        "/api/roles": {
            "get": {
                "tags": [
                    "Roles"
                ],
                "summary": "Get all roles",
                "description": "Display a listing of the resource.",
                "operationId": "77e3636d8592997ce9d6d27b50857a69",
                "responses": {
                    "200": {
                        "description": "List of roles",
                        "content": {
                            "application/json": {
                                "schema": {
                                    "properties": {
                                        "success": {
                                            "type": "boolean",
                                            "example": true
                                        },
                                        "data": {
                                            "type": "array",
                                            "items": {
                                                "properties": {
                                                    "id": {
                                                        "type": "integer",
                                                        "example": 1
                                                    },
                                                    "name": {
                                                        "type": "string",
                                                        "example": "Manager"
                                                    },
                                                    "permissions": {
                                                        "type": "array",
                                                        "items": {
                                                            "properties": {
                                                                "id": {
                                                                    "type": "integer",
                                                                    "example": 1
                                                                },
                                                                "name": {
                                                                    "type": "string",
                                                                    "example": "Read Users"
                                                                },
                                                                "type ": {
                                                                    "type": "string",
                                                                    "example": "read"
                                                                },
                                                                "group": {
                                                                    "type": "string",
                                                                    "example": "users"
                                                                }
                                                            },
                                                            "type": "object"
                                                        }
                                                    }
                                                },
                                                "type": "object"
                                            }
                                        }
                                    },
                                    "type": "object"
                                }
                            }
                        }
                    },
                    "401": {
                        "description": "Unauthenticated"
                    },
                    "403": {
                        "description": "User is authenticated, but dont have permission **Read Roles** to access this resource"
                    },
                    "422": {
                        "description": "Validation error"
                    },
                    "500": {
                        "description": "Internal server error"
                    }
                },
                "security": [
                    {
                        "bearerAuth": []
                    }
                ]
            },
            "post": {
                "tags": [
                    "Roles"
                ],
                "summary": "Create a new role",
                "description": "Store a newly created resource in storage.",
                "operationId": "4a563842fbfcad237f63da43065fca3d",
                "requestBody": {
                    "required": true,
                    "content": {
                        "application/json": {
                            "schema": {
                                "required": [
                                    "name"
                                ],
                                "properties": {
                                    "name": {
                                        "type": "string",
                                        "example": "Manager"
                                    },
                                    "permissions": {
                                        "type": "array",
                                        "items": {
                                            "type": "integer"
                                        },
                                        "example": [
                                            1,
                                            2,
                                            3
                                        ]
                                    }
                                },
                                "type": "object"
                            }
                        }
                    }
                },
                "responses": {
                    "201": {
                        "description": "Role created successfully",
                        "content": {
                            "application/json": {
                                "schema": {
                                    "properties": {
                                        "success": {
                                            "type": "boolean",
                                            "example": true
                                        },
                                        "message": {
                                            "type": "string",
                                            "example": "Role created successfully"
                                        },
                                        "data": {
                                            "properties": {
                                                "id": {
                                                    "type": "integer",
                                                    "example": 1
                                                },
                                                "name": {
                                                    "type": "string",
                                                    "example": "Manager"
                                                },
                                                "permissions": {
                                                    "type": "array",
                                                    "items": {
                                                        "properties": {
                                                            "id": {
                                                                "type": "integer",
                                                                "example": 1
                                                            },
                                                            "name": {
                                                                "type": "string",
                                                                "example": "Read Users"
                                                            },
                                                            "type": {
                                                                "type": "string",
                                                                "example": "read"
                                                            },
                                                            "group": {
                                                                "type": "string",
                                                                "example": "users"
                                                            }
                                                        },
                                                        "type": "object"
                                                    }
                                                }
                                            },
                                            "type": "object"
                                        }
                                    },
                                    "type": "object"
                                }
                            }
                        }
                    },
                    "401": {
                        "description": "Unauthenticated"
                    },
                    "403": {
                        "description": "User is authenticated, but dont have permission **Create Roles** to access this resource"
                    },
                    "422": {
                        "description": "Validation error"
                    },
                    "500": {
                        "description": "Internal server error"
                    }
                },
                "security": [
                    {
                        "bearerAuth": []
                    }
                ]
            }
        },
        "/api/roles/{role}": {
            "get": {
                "tags": [
                    "Roles"
                ],
                "summary": "Get a role by ID",
                "description": "Display the specified resource.",
                "operationId": "f917de2b9b752dd8759d69202136b7ff",
                "parameters": [
                    {
                        "name": "role",
                        "in": "path",
                        "required": true,
                        "schema": {
                            "type": "integer"
                        }
                    }
                ],
                "responses": {
                    "200": {
                        "description": "Role found",
                        "content": {
                            "application/json": {
                                "schema": {
                                    "properties": {
                                        "success": {
                                            "type": "boolean",
                                            "example": true
                                        },
                                        "data": {
                                            "properties": {
                                                "id": {
                                                    "type": "integer",
                                                    "example": 1
                                                },
                                                "name": {
                                                    "type": "string",
                                                    "example": "Manager"
                                                },
                                                "permissions": {
                                                    "type": "array",
                                                    "items": {
                                                        "properties": {
                                                            "id": {
                                                                "type": "integer",
                                                                "example": 1
                                                            },
                                                            "name": {
                                                                "type": "string",
                                                                "example": "Read Users"
                                                            },
                                                            "type": {
                                                                "type": "string",
                                                                "example": "read"
                                                            },
                                                            "group": {
                                                                "type": "string",
                                                                "example": "users"
                                                            }
                                                        },
                                                        "type": "object"
                                                    }
                                                }
                                            },
                                            "type": "object"
                                        }
                                    },
                                    "type": "object"
                                }
                            }
                        }
                    },
                    "401": {
                        "description": "Unauthenticated"
                    },
                    "403": {
                        "description": "User is authenticated, but dont have permission **Read Roles** to access this resource"
                    },
                    "404": {
                        "description": "Role not found"
                    },
                    "422": {
                        "description": "Validation error"
                    },
                    "500": {
                        "description": "Internal server error"
                    }
                },
                "security": [
                    {
                        "bearerAuth": []
                    }
                ]
            },
            "put": {
                "tags": [
                    "Roles"
                ],
                "summary": "Update a role by ID",
                "description": "Update the specified resource in storage.",
                "operationId": "1509723c88cb1e49be3ecc047204f64a",
                "parameters": [
                    {
                        "name": "role",
                        "in": "path",
                        "required": true,
                        "schema": {
                            "type": "integer"
                        }
                    }
                ],
                "requestBody": {
                    "required": true,
                    "content": {
                        "application/json": {
                            "schema": {
                                "required": [
                                    "name"
                                ],
                                "properties": {
                                    "name": {
                                        "type": "string",
                                        "example": "Manager"
                                    },
                                    "permissions": {
                                        "type": "array",
                                        "items": {
                                            "type": "integer"
                                        },
                                        "example": [
                                            1,
                                            2,
                                            3
                                        ]
                                    }
                                },
                                "type": "object"
                            }
                        }
                    }
                },
                "responses": {
                    "200": {
                        "description": "Role updated successfully",
                        "content": {
                            "application/json": {
                                "schema": {
                                    "properties": {
                                        "success": {
                                            "type": "boolean",
                                            "example": true
                                        },
                                        "message": {
                                            "type": "string",
                                            "example": "Role updated successfully"
                                        },
                                        "data": {
                                            "properties": {
                                                "id": {
                                                    "type": "integer",
                                                    "example": 1
                                                },
                                                "name": {
                                                    "type": "string",
                                                    "example": "Manager"
                                                },
                                                "permissions": {
                                                    "type": "array",
                                                    "items": {
                                                        "properties": {
                                                            "id": {
                                                                "type": "integer",
                                                                "example": 1
                                                            },
                                                            "name": {
                                                                "type": "string",
                                                                "example": "Read Users"
                                                            },
                                                            "type": {
                                                                "type": "string",
                                                                "example": "read"
                                                            },
                                                            "group": {
                                                                "type": "string",
                                                                "example": "users"
                                                            }
                                                        },
                                                        "type": "object"
                                                    }
                                                }
                                            },
                                            "type": "object"
                                        }
                                    },
                                    "type": "object"
                                }
                            }
                        }
                    },
                    "401": {
                        "description": "Unauthenticated"
                    },
                    "403": {
                        "description": "User is authenticated, but dont have permission **Update Roles** to access this resource"
                    },
                    "404": {
                        "description": "Role not found"
                    },
                    "422": {
                        "description": "Validation error"
                    },
                    "500": {
                        "description": "Internal server error"
                    }
                },
                "security": [
                    {
                        "bearerAuth": []
                    }
                ]
            },
            "delete": {
                "tags": [
                    "Roles"
                ],
                "summary": "Delete a role by ID",
                "description": "Remove the specified resource from storage.\nReassigns users from deleted role to a replacement role.",
                "operationId": "b96c05ea55ef4e3d29464b1b62c469aa",
                "parameters": [
                    {
                        "name": "role",
                        "in": "path",
                        "required": true,
                        "schema": {
                            "type": "integer"
                        }
                    }
                ],
                "requestBody": {
                    "required": true,
                    "content": {
                        "application/json": {
                            "schema": {
                                "required": [
                                    "replacement_role_id"
                                ],
                                "properties": {
                                    "replacement_role_id": {
                                        "type": "integer",
                                        "example": 1
                                    }
                                },
                                "type": "object"
                            }
                        }
                    }
                },
                "responses": {
                    "200": {
                        "description": "Role deleted successfully",
                        "content": {
                            "application/json": {
                                "schema": {
                                    "properties": {
                                        "success": {
                                            "type": "boolean",
                                            "example": true
                                        },
                                        "message": {
                                            "type": "string"
                                        },
                                        "reassigned_users_count": {
                                            "type": "integer"
                                        },
                                        "replacement_role": {
                                            "type": "string"
                                        }
                                    },
                                    "type": "object"
                                }
                            }
                        }
                    },
                    "401": {
                        "description": "Unauthenticated"
                    },
                    "403": {
                        "description": "User is authenticated, but dont have permission **Delete Roles** to access this resource"
                    },
                    "404": {
                        "description": "Role not found"
                    },
                    "422": {
                        "description": "Validation error"
                    },
                    "500": {
                        "description": "Failed to delete role"
                    }
                },
                "security": [
                    {
                        "bearerAuth": []
                    }
                ]
            }
        }
    },
    "components": {
        "securitySchemes": {
            "bearerAuth": {
                "type": "http",
                "bearerFormat": "JWT",
                "scheme": "bearer"
            }
        }
    },
    "tags": [
        {
            "name": "Authentication",
            "description": "Authentication"
        },
        {
            "name": "Permissions",
            "description": "Permissions"
        },
        {
            "name": "Roles",
            "description": "Roles"
        }
    ]
}